erc20token/__init__.py
erc20token/exceptions.py
erc20token/provider.py
erc20token/sdk.py
erc20token/utils.py
erc20token/version.py
erc20token_python-0.1.10.dist-info/LICENSE
erc20token_python-0.1.10.dist-info/METADATA
erc20token_python-0.1.10.dist-info/WHEEL
erc20token_python-0.1.10.dist-info/top_level.txt
erc20token_python-0.1.10.dist-info/RECORD
