Metadata-Version: 2.1
Name: erc20token-python
Version: 0.1.10
Summary: ERC20 token SDK for Python
Home-page: https://github.com/growlot/erc20token-sdk-python
Author: Kin Foundation
Author-email: david.bolshoy@kik.com
Maintainer: imperchik
Maintainer-email: imperchik@gmail.com
License: GPLv2
Keywords: ethereum,erc20,blockchain,cryptocurrency
Platform: UNKNOWN
Classifier: License :: OSI Approved :: GNU General Public License v2 (GPLv2)
Classifier: Intended Audience :: Developers
Classifier: Development Status :: 4 - Beta
Classifier: Topic :: Software Development :: Libraries :: Python Modules
Classifier: Programming Language :: Python
Classifier: Programming Language :: Python :: 3
Requires-Python: >=3.6.6
Requires-Dist: asn1crypto (>=0.23.0)
Requires-Dist: backoff (>=1.4.3)
Requires-Dist: certifi (>=2017.11.5)
Requires-Dist: cffi (>=1.11.2)
Requires-Dist: chardet (>=3.0.4)
Requires-Dist: coincurve (>=6.0.0)
Requires-Dist: cytoolz (>=0.8.2)
Requires-Dist: ethereum (>=2.2.0)
Requires-Dist: ethereum-abi-utils (==0.4.4)
Requires-Dist: ethereum-keys (==0.1.0a7)
Requires-Dist: ethereum-tester (==0.1.0b2)
Requires-Dist: ethereum-utils (==0.6.0)
Requires-Dist: future (>=0.16.0)
Requires-Dist: idna (>=2.6)
Requires-Dist: pbkdf2 (>=1.3)
Requires-Dist: py (>=1.5.2)
Requires-Dist: py-ecc (>=1.4.2)
Requires-Dist: pycparser (>=2.18)
Requires-Dist: pycryptodome (>=3.4.7)
Requires-Dist: pyethash (>=0.1.27)
Requires-Dist: pylru (>=1.0.9)
Requires-Dist: pysha3 (>=1.0.2)
Requires-Dist: PyYAML (>=3.12)
Requires-Dist: repoze.lru (>=0.7)
Requires-Dist: requests (>=2.18.4)
Requires-Dist: rlp (>=0.6.0)
Requires-Dist: scrypt (>=0.8.0)
Requires-Dist: semantic-version (>=2.6.0)
Requires-Dist: toolz (>=0.8.2)
Requires-Dist: urllib3 (>=1.22)
Requires-Dist: web3 (==3.16.3)
